vercel/env.py
vercel/env.pyi
vercel_functions-0.1.4.dist-info/licenses/LICENSE.md
vercel_functions-0.1.4.dist-info/WHEEL
vercel_functions-0.1.4.dist-info/METADATA
vercel_functions-0.1.4.dist-info/RECORD
